[
    {
        "name": "Mesa Gamer Cougar Electrical E-Mars 150 RGB USB - Negro",
        "price": "Gs. 6.369.000",
        "details": {
            "Diseño": "Moderno y resistente",
            "Iluminación": "RGB",
            "Conectores": "HDMI, USB-C, USB-A, entrada de micrófono, auricular, y botón RGB",
            "Elevación máxima": "100 kg",
            "Tamaño": "150 x 115 x 71 cm"
        },
        "label": "Cougar",
        "categories": [
            "Informática",
            "Accesorios"
        ],
        "srcImages": [
            "https://nissei.com/media/catalog/product/cache/ef70040224a801a7e53890035f03a841/p/r/proyecto_nuevo_42_.jpg",
            "https://nissei.com/media/catalog/product/cache/ef70040224a801a7e53890035f03a841/p/r/proyecto_nuevo_43__1.jpg",
            "https://nissei.com/media/catalog/product/cache/ef70040224a801a7e53890035f03a841/p/r/proyecto_nuevo_45_.jpg",
            "https://nissei.com/media/catalog/product/cache/ef70040224a801a7e53890035f03a841/p/r/proyecto_nuevo_44__1.jpg",
            "https://nissei.com/media/catalog/product/cache/ef70040224a801a7e53890035f03a841/p/r/proyecto_nuevo_47_.jpg",
            "https://nissei.com/media/catalog/product/cache/ef70040224a801a7e53890035f03a841/p/r/proyecto_nuevo_46_.jpg"
        ],
        "id": 1
    },
    {
        "name": "Soporte para Monitor Stalo Triple",
        "price": "Gs. 151.050",
        "details": {
            "Diseño": "Moderno y resistente",
            "Ofrece": "Comodidad y estabilidad al estudiar o trabajar",
            "Material": "MDF y acabado UV",
            "Capacidad": "40kg",
            "Dimensiones": "16 x 24 x 35 cm"
        },
        "label": "Stalo",
        "categories": [
            "Informática",
            "Soporte para Monitores",
            "Muebles",
            "Soporte para TV's y Monitores"
        ],
        "srcImages": [
            "https://nissei.com/media/catalog/product/cache/ef70040224a801a7e53890035f03a841/r/p/rpm-1003128-100-corregido-2.jpg",
            "https://nissei.com/media/catalog/product/cache/ef70040224a801a7e53890035f03a841/r/p/rpm-1003128-100-corregido-1.jpg"
        ],
        "id": 2
    },
    {
        "name": "Soporte P1-Pro para Notebook - Rosa",
        "price": "Gs. 39.706",
        "details": {
            "Diseño": "Plegable y portátil",
            "Ofrece": "Comodidad y estabilidad al estudiar o trabajar",
            "Material": "ABS y aleación de aluminio",
            "Compatible con": "Notebooks de hasta 17\""
        },
        "label": "Generico",
        "categories": [
            "Informática",
            "Accesorios",
            "Librería"
        ],
        "srcImages": [
            "https://nissei.com/media/catalog/product/cache/ef70040224a801a7e53890035f03a841/r/p/rpm-1003293-1_1.jpg"
        ],
        "id": 3
    },
    {
        "name": "Soporte P1-Pro para Notebook",
        "price": "Gs. 39.706",
        "details": {
            "Diseño": "Plegable y portátil",
            "Ofrece": "Comodidad y estabilidad al estudiar o trabajar",
            "Material": "ABS y aleación de aluminio",
            "Compatible con": "Notebooks de hasta 17\""
        },
        "label": "Generico",
        "categories": [
            "Informática",
            "Accesorios",
            "Librería"
        ],
        "srcImages": [
            "https://nissei.com/media/catalog/product/cache/ef70040224a801a7e53890035f03a841/r/p/rpm-1003293-1.jpg",
            "https://nissei.com/media/catalog/product/cache/ef70040224a801a7e53890035f03a841/r/p/rpm-1004365-1.jpg",
            "https://nissei.com/media/catalog/product/cache/ef70040224a801a7e53890035f03a841/r/p/rpm-1003948-1.jpg"
        ],
        "id": 4
    },
    {
        "name": "Mini PC Radxa Rock 4 SE",
        "price": "Gs. 826.000",
        "details": {
            "Procesador": "Rockchip RK3399-T",
            "Memoria RAM": "4 GB LPDDR4",
            "Interfaz": "Jack 3.5 mm, USB, micro USB, HDMI y RJ-45",
            "Conectividad": "Wi-Fi y Bluetooth 5.0"
        },
        "label": "Radxa",
        "categories": [
            "Informática",
            "Desktops"
        ],
        "srcImages": [
            "https://nissei.com/media/catalog/product/cache/ef70040224a801a7e53890035f03a841/1/0/101967-2.jpg",
            "https://nissei.com/media/catalog/product/cache/ef70040224a801a7e53890035f03a841/1/0/101967-1.jpg"
        ],
        "id": 5
    },
    {
        "name": "Proyector OnLed On7 720P",
        "price": "Gs. 1.167.000",
        "details": {
            "Sistema de imagen": "LCD",
            "Relación de aspecto": "16",
            "Resolución nativa": "720P",
            "Entradas": "HD, USB, SD y AV",
            "Reproducción de video": "MPEG1, MPEG2, MPEG4, RM, RMVB, H264, MOV, MJPEG, FLV, DIVX",
            "Reproducción de audio": "WMA, MP3 y M4A"
        },
        "label": "Onled",
        "categories": [
            "Proyectores y Pantallas",
            "Informática"
        ],
        "srcImages": [
            "https://nissei.com/media/catalog/product/cache/ef70040224a801a7e53890035f03a841/i/m/img_01.jpg",
            "https://nissei.com/media/catalog/product/cache/ef70040224a801a7e53890035f03a841/m/g/mg_02.jpg",
            "https://nissei.com/media/catalog/product/cache/ef70040224a801a7e53890035f03a841/m/g/mg_03.jpg"
        ],
        "id": 6
    },
    {
        "name": "Desktop All In One HP 200 G4 Intel Pentium J5040 - Negro",
        "price": "Gs. 3.454.000",
        "details": {
            "Pantalla": "IPS de 21.5\" con resolución Full HD 1920 x 1080p",
            "Procesador": "Intel Pentium Silver J5040 Quad-Core 2.0 - 3.2 GHz",
            "Memoria RAM": "DDR4 de 4 GB",
            "Memoria de almacenamiento": "HDD de 1 TB",
            "Gráficos": "Intel UHD 605",
            "Sistema operativo": "FreeDos"
        },
        "label": "HP",
        "categories": [
            "Informática",
            "Desktops",
            "All in one"
        ],
        "srcImages": [
            "https://nissei.com/media/catalog/product/cache/ef70040224a801a7e53890035f03a841/p/c/pc_all_in_one_hp_200_g4_-_1.jpg",
            "https://nissei.com/media/catalog/product/cache/ef70040224a801a7e53890035f03a841/p/c/pc_all_in_one_hp_200_g4_-_2.jpg",
            "https://nissei.com/media/catalog/product/cache/ef70040224a801a7e53890035f03a841/p/c/pc_all_in_one_hp_200_g4_-_3.jpg",
            "https://nissei.com/media/catalog/product/cache/ef70040224a801a7e53890035f03a841/p/c/pc_all_in_one_hp_200_g4_-_4_1.jpg"
        ],
        "id": 7
    },
    {
        "name": "Cooler Satellite A-CP03 para Notebook - Negro",
        "price": "Gs. 72.000",
        "details": {
            "Ventilador": "160 mm",
            "Interfaz": "USB",
            "Velocidad del ventilador": "900 RPM",
            "Material": "Metal, plástico",
            "Compatibilidad": "9\" a 17\""
        },
        "label": "Satellite",
        "categories": [
            "Informática"
        ],
        "srcImages": [
            "https://nissei.com/media/catalog/product/cache/ef70040224a801a7e53890035f03a841/c/o/cooler_satellite.jpg"
        ],
        "id": 8
    },
    {
        "name": "Cooler Satellite A-CP19 para Notebook - Negro",
        "price": "Gs. 81.000",
        "details": {
            "Ventilador": "140 mm",
            "Interfaz": "USB",
            "Velocidad del ventilador": "900 RPM",
            "Material": "Plástico, metal",
            "Compatibilidad": "9\" a 17\""
        },
        "label": "Satellite",
        "categories": [
            "Informática"
        ],
        "srcImages": [
            "https://nissei.com/media/catalog/product/cache/ef70040224a801a7e53890035f03a841/s/a/sate_19.jpg"
        ],
        "id": 9
    },
    {
        "name": "Cooler Satellite A-CP20 Para Notebook - Negro",
        "price": "Gs. 72.000",
        "details": {
            "Ventilador": "140 mm",
            "Interfaz": "USB",
            "Velocidad del ventilador": "1600 RPM",
            "Material": "Metal, plástico",
            "Compatibilidad": "9\" a 17\""
        },
        "label": "Satellite",
        "categories": [
            "Informática"
        ],
        "srcImages": [
            "https://nissei.com/media/catalog/product/cache/ef70040224a801a7e53890035f03a841/s/a/sate_20.jpg"
        ],
        "id": 10
    },
    {
        "name": "Speaker Para PC Logitech Z313 - Negro",
        "price": "Gs. 346.000",
        "details": {
            "Canales de salida de audio": "2.1",
            "Potencia estimada RMS": "25 W",
            "Control con cable": "Encendido, volumen, Jack 3.5 mm",
            "Conectividad": "Jack 3.5 mm"
        },
        "label": "Logitech",
        "categories": [
            "Informática",
            "Accesorios"
        ],
        "srcImages": [
            "https://nissei.com/media/catalog/product/cache/ef70040224a801a7e53890035f03a841/z/3/z313-computer-speaker-system.jpg",
            "https://nissei.com/media/catalog/product/cache/ef70040224a801a7e53890035f03a841/z/3/z313-computer-speaker-system_1_.jpg",
            "https://nissei.com/media/catalog/product/cache/ef70040224a801a7e53890035f03a841/z/3/z313-computer-speaker-system_2__1.jpg",
            "https://nissei.com/media/catalog/product/cache/ef70040224a801a7e53890035f03a841/z/3/z313-computer-speaker-system_3_.jpg"
        ],
        "id": 11
    },
    {
        "name": "Mouse Inalámbrico Logitech M187 - Negro (910-005459)",
        "price": "Gs. 99.000",
        "details": {
            "Diseño": "Compacto",
            "Tipo de mouse": "Óptico",
            "Resolución": "1000 DPI",
            "Interfaz": "Receptor USB"
        },
        "label": "Logitech",
        "categories": [
            "Informática",
            "Mouses & Pads"
        ],
        "srcImages": [
            "https://nissei.com/media/catalog/product/cache/ef70040224a801a7e53890035f03a841/m/1/m187-negro_910-005459.jpg",
            "https://nissei.com/media/catalog/product/cache/ef70040224a801a7e53890035f03a841/m/1/m187-negro-910-005459-1.jpg"
        ],
        "id": 12
    },
    {
        "name": "Mouse Inalámbrico Logitech M187 - Blossom (910-005364)",
        "price": "Gs. 99.000",
        "details": {
            "Diseño": "Compacto",
            "Tipo de mouse": "Óptico",
            "Resolución": "1000 DPI",
            "Interfaz": "Receptor USB"
        },
        "label": "Logitech",
        "categories": [
            "Informática",
            "Mouses & Pads"
        ],
        "srcImages": [
            "https://nissei.com/media/catalog/product/cache/ef70040224a801a7e53890035f03a841/m/1/m187-blossom_910-005364_-001.jpg",
            "https://nissei.com/media/catalog/product/cache/ef70040224a801a7e53890035f03a841/m/1/m187-blossom-910-005364_-002.jpg"
        ],
        "id": 13
    },
    {
        "name": "Mouse Inalámbrico Logitech M187 - Coral (910-005362)",
        "price": "Gs. 99.000",
        "details": {
            "Diseño": "Compacto",
            "Tipo de mouse": "Óptico",
            "Resolución": "1000 DPI",
            "Interfaz": "Receptor USB"
        },
        "label": "Logitech",
        "categories": [
            "Informática",
            "Mouses & Pads"
        ],
        "srcImages": [
            "https://nissei.com/media/catalog/product/cache/ef70040224a801a7e53890035f03a841/m/1/m187-coral910-005362_-01.jpg",
            "https://nissei.com/media/catalog/product/cache/ef70040224a801a7e53890035f03a841/m/1/m187-coral910-005362_-002.jpg"
        ],
        "id": 14
    },
    {
        "name": "Mouse Inalámbrico Logitech M187",
        "price": "Gs. 99.000",
        "details": {
            "Diseño": "Compacto",
            "Tipo de mouse": "Óptico",
            "Resolución": "1000 DPI",
            "Conectividad": "Receptor USB"
        },
        "label": "Logitech",
        "categories": [
            "Informática",
            "Mouses & Pads"
        ],
        "srcImages": [
            "https://nissei.com/media/catalog/product/cache/ef70040224a801a7e53890035f03a841/l/o/logitech_m187_mini_light_blue_910-005363_-_2_1.jpg",
            "https://nissei.com/media/catalog/product/cache/ef70040224a801a7e53890035f03a841/m/1/m187-azul_2.jpg",
            "https://nissei.com/media/catalog/product/cache/ef70040224a801a7e53890035f03a841/m/1/m187-blossom_2.jpg",
            "https://nissei.com/media/catalog/product/cache/ef70040224a801a7e53890035f03a841/m/1/m187-coral_2.jpg",
            "https://nissei.com/media/catalog/product/cache/ef70040224a801a7e53890035f03a841/m/1/m187-negro_2.jpg"
        ],
        "id": 15
    },
    {
        "name": "Cooler Liquido Redragon CCW-3000 Effect X RGB para CPU - Negro",
        "price": "Gs. 717.000",
        "details": {
            "Velocidad del ventilador": "800-1600 RPM ± 200",
            "Flujo de aire": "65.5 CFM ± 10%",
            "Iluminación": "Led RGB (ARGB)",
            "Alimentacion": "12V DC",
            "Compatibilidad": "AMD, Intel"
        },
        "label": "REDRAGON",
        "categories": [
            "Informática",
            "Componentes"
        ],
        "srcImages": [
            "https://nissei.com/media/catalog/product/cache/ef70040224a801a7e53890035f03a841/c/o/cooler_1_1.jpg",
            "https://nissei.com/media/catalog/product/cache/ef70040224a801a7e53890035f03a841/c/o/cooler_redragon.jpg",
            "https://nissei.com/media/catalog/product/cache/ef70040224a801a7e53890035f03a841/c/o/cooloer.jpg"
        ],
        "specifications": {
            "Socket CPU": "Intel",
            "Dimensiones": "274x120x25mm",
            "Material": "Aluminio",
            "Dimensión del ventilador": "120x120x25mm",
            "Velocidad del ventilador": "800-1600 RPM ± 200",
            "Flujo de aire": "65.5 CFM ± 10%",
            "Presión del aire": "1.88 mm H2O (Max)",
            "Nivel de ruido": "26.9dB",
            "Iluminación": "Led RGB (ARGB)",
            "Conexión": "4-Pin PWM + 3-pin ARGB",
            "Voltaje": "12V DC",
            "Corriente eléctrica": "0.30A",
            "Consumo": "3.6W",
            "TDP": "140W",
            "Dimensiones de la bomba": "69x69x45mm",
            "Material del contacto": "Cobre",
            "Velocidad de rotación": "2200 RPM ± 10%"
        },
        "id": 16
    },
    {
        "name": "Lector de Código de Barra Zkteco ZKB101 - Negro",
        "price": "Gs. 225.000",
        "details": {
            "Tipo": "Escáner láser rojo de 32 bits",
            "Ángulo de lectura": "70°, 70° (vertical, horizontal)",
            "Velocidad de escaneo": "300 veces/segundo",
            "Precisión": "Mayor o igual a 3000",
            "Interfaz compatible": "RJ-45, USB"
        },
        "label": "ZKTECO",
        "categories": [
            "Accesorios",
            "Informática"
        ],
        "srcImages": [
            "https://nissei.com/media/catalog/product/cache/ef70040224a801a7e53890035f03a841/6/8/68051_1.jpg"
        ],
        "id": 17
    },
    {
        "name": "Notebook Dell Latitude 3520 15.6\" Intel Core i5-1135G7 8 GB 1 TB HDD - Negro",
        "price": "Gs. 3.678.000",
        "details": {
            "Pantalla": "LED 15.6\" HD 1366 x 768p",
            "Procesador": "Intel Core i5-1135G7 Quad-Core 2.4 - 4.2 GHz",
            "Memoria RAM": "8 GB DDR4",
            "Memoria de almacenamiento": "HDD de 1 TB",
            "Gráficos": "Intel Iris Xe",
            "Sistema operativo": "Windows 11"
        },
        "label": "Dell",
        "categories": [
            "Notebooks Estudio",
            "Notebooks Trabajo",
            "Ten to Ten"
        ],
        "srcImages": [
            "https://nissei.com/media/catalog/product/cache/ef70040224a801a7e53890035f03a841/1/1/112149-3520-5.jpg",
            "https://nissei.com/media/catalog/product/cache/ef70040224a801a7e53890035f03a841/1/1/112149-3520-4.jpg",
            "https://nissei.com/media/catalog/product/cache/ef70040224a801a7e53890035f03a841/1/1/112149-3520-3.jpg",
            "https://nissei.com/media/catalog/product/cache/ef70040224a801a7e53890035f03a841/1/1/112149-3520-2.jpg",
            "https://nissei.com/media/catalog/product/cache/ef70040224a801a7e53890035f03a841/1/1/112149-3520-1.jpg"
        ],
        "id": 18
    },
    {
        "name": "Notebook Dell Inspiron 15 3530 15.6\" Intel Core i7-1355U 16 GB DDR4 512 SSD Touch - Negro",
        "price": "Gs. 8.252.000",
        "details": {
            "Pantalla": "LED de 15.6\" Full HD 1920 x 1080p",
            "Procesador": "Intel Core i7-1355U Deca-Core 1.7 - 5.0 GHz",
            "Memoria RAM": "16 GB DDR4",
            "Memoria de almacenamiento": "SSD M.2 NVMe de 512 GB",
            "Gráficos": "Intel Iris Xe",
            "Sistema operativo": "Windows 11 Home"
        },
        "label": "Dell",
        "categories": [
            "Notebooks Estudio",
            "Notebooks Trabajo"
        ],
        "srcImages": [
            "https://nissei.com/media/catalog/product/cache/ef70040224a801a7e53890035f03a841/1/1/112036-i3530-7050blk-pus-5.jpg",
            "https://nissei.com/media/catalog/product/cache/ef70040224a801a7e53890035f03a841/1/1/112036-i3530-7050blk-pus-4.jpg",
            "https://nissei.com/media/catalog/product/cache/ef70040224a801a7e53890035f03a841/1/1/112036-i3530-7050blk-pus-3.jpg",
            "https://nissei.com/media/catalog/product/cache/ef70040224a801a7e53890035f03a841/1/1/112036-i3530-7050blk-pus-2.jpg",
            "https://nissei.com/media/catalog/product/cache/ef70040224a801a7e53890035f03a841/1/1/112036-i3530-7050blk-pus-1.jpg"
        ],
        "id": 19
    },
    {
        "name": "Notebook Lenovo IdeaPad 3 14IT05 14\" Intel Core i5-1135G7 8 GB DDR4 512 GB SSD - Platinum Grey (81X700FXUS)",
        "price": "Gs. 3.947.000",
        "details": {
            "Pantalla": "TN de 14\" Full HD 1920 x 1080p",
            "Procesador": "Intel Core i5-1135G7 Quad-Core 2.4 - 4.2 GHz",
            "Memoria RAM": "8 GB DDR4",
            "Memoria de almacenamiento": "SSD M.2 NVMe de 512 GB",
            "Gráficos": "Intel Iris Xe",
            "Sistema operativo": "Windows 11 Home"
        },
        "label": "Lenovo",
        "categories": [
            "Notebooks Estudio",
            "Notebooks Trabajo"
        ],
        "srcImages": [
            "https://nissei.com/media/catalog/product/cache/ef70040224a801a7e53890035f03a841/1/1/111949-14it05-4.jpg",
            "https://nissei.com/media/catalog/product/cache/ef70040224a801a7e53890035f03a841/1/1/111949-14it05-3.jpg",
            "https://nissei.com/media/catalog/product/cache/ef70040224a801a7e53890035f03a841/1/1/111949-14it05-2.jpg",
            "https://nissei.com/media/catalog/product/cache/ef70040224a801a7e53890035f03a841/1/1/111949-14it05-1.jpg"
        ],
        "id": 20
    },
    {
        "name": "Notebook HP Pavilion 15-EG3045CL 15.6\" Intel Core i7-1355U MX 550 2 GB Touch - Azul",
        "price": "Gs. 8.064.000",
        "details": {
            "Pantalla": "LED táctil de 15.6\" Full HD 1920 x 1080p",
            "Procesador": "Intel Core i7-1355U Deca-Core 1.7 - 5.0 GHz",
            "Memoria RAM": "16 GB DDR4",
            "Memoria de almacenamiento": "SSD M.2 NVMe de 512 GB",
            "Gráficos": "NVIDIA GeForce MX 550 2 GB GDDR6",
            "Sistema operativo": "Windows 11 Home"
        },
        "label": "HP",
        "categories": [
            "Notebooks Estudio",
            "Notebooks Trabajo"
        ],
        "srcImages": [
            "https://nissei.com/media/catalog/product/cache/ef70040224a801a7e53890035f03a841/1/1/111376-15-eg304-4.jpg",
            "https://nissei.com/media/catalog/product/cache/ef70040224a801a7e53890035f03a841/1/1/111376-15-eg304-3.jpg",
            "https://nissei.com/media/catalog/product/cache/ef70040224a801a7e53890035f03a841/1/1/111376-15-eg304-2.jpg",
            "https://nissei.com/media/catalog/product/cache/ef70040224a801a7e53890035f03a841/1/1/111376-15-eg304-1.jpg"
        ],
        "id": 21
    },
    {
        "name": "Notebook HP 15-DY2792WM 15.6\" Intel Core i3-1115G4 8 GB DDR4 256 GB SSD - Azul",
        "price": "Gs. 3.355.000",
        "details": {
            "Pantalla": "LED de 15.6\" HD 1366 x 768p",
            "Procesador": "Intel Core i3-1115G4 Dual-Core 3.0 - 4.1 GHz",
            "Memoria RAM": "8 GB DDR4",
            "Memoria de almacenamiento": "SSD M.2 NVMe de 256 GB",
            "Gráficos": "Intel UHD",
            "Sistema operativo": "Windows 11 Home"
        },
        "label": "HP",
        "categories": [
            "Notebooks Estudio",
            "Notebooks Trabajo",
            "Ten to Ten"
        ],
        "srcImages": [
            "https://nissei.com/media/catalog/product/cache/ef70040224a801a7e53890035f03a841/1/1/111954-15-dy2792wm-3.jpg",
            "https://nissei.com/media/catalog/product/cache/ef70040224a801a7e53890035f03a841/1/1/111954-15-dy2792wm-2.jpg",
            "https://nissei.com/media/catalog/product/cache/ef70040224a801a7e53890035f03a841/1/1/111954-15-dy2792wm-1.jpg"
        ],
        "id": 22
    },
    {
        "name": "Notebook HP 15-DY2702DX 15.6\" Intel Core i3-1115G4 8 GB DDR4 256 GB SSD Touch - Plata",
        "price": "Gs. 3.517.000",
        "details": {
            "Pantalla": "LED táctil de 15.6\" HD 1366 x 768p",
            "Procesador": "Intel Core i3-1115G4 Dual-Core 3.0 - 4.1 GHz",
            "Memoria RAM": "8 GB DDR4",
            "Memoria de almacenamiento": "SSD M.2 NVMe de 256 GB",
            "Gráficos": "Intel UHD",
            "Sistema operativo": "Windows 11 Home"
        },
        "label": "HP",
        "categories": [
            "Notebooks Estudio",
            "Notebooks Trabajo"
        ],
        "srcImages": [
            "https://nissei.com/media/catalog/product/cache/ef70040224a801a7e53890035f03a841/1/1/112022-15-dy2702dx-34.jpg",
            "https://nissei.com/media/catalog/product/cache/ef70040224a801a7e53890035f03a841/1/1/112022-15-dy2702dx-3.jpg",
            "https://nissei.com/media/catalog/product/cache/ef70040224a801a7e53890035f03a841/1/1/112022-15-dy2702dx-2.jpg",
            "https://nissei.com/media/catalog/product/cache/ef70040224a801a7e53890035f03a841/1/1/112022-15-dy2702dx-1.jpg"
        ],
        "id": 23
    },
    {
        "name": "Notebook/Tablet Asus Zenbook 14 Flip OLED UP3404VA-KN073W 14\" Intel Core i7-1165G7 16 GB DDR4 512 GB SSD - Ponder Blue",
        "price": "Gs. 11.212.000",
        "details": {
            "Pantalla": "OLED táctil de 14\" WQXGA+ 2880 x 1800p",
            "Procesador": "Intel Core i7-1360p Dodeca-Core 2.2 - 5.0 GHz",
            "Memoria RAM": "16 GB LPDDR5",
            "Memoria de almacenamiento": "SSD M.2 NVMe de 512 GB",
            "Gráficos": "Intel Iris Xe",
            "Sistema operativo": "Windows 11 Home"
        },
        "label": "Asus",
        "categories": [
            "Notebooks Estudio",
            "Notebooks Trabajo"
        ],
        "srcImages": [
            "https://nissei.com/media/catalog/product/cache/ef70040224a801a7e53890035f03a841/1/1/110156-up3404va-kn073w-7.jpg",
            "https://nissei.com/media/catalog/product/cache/ef70040224a801a7e53890035f03a841/1/1/110156-up3404va-kn073w-6.jpg",
            "https://nissei.com/media/catalog/product/cache/ef70040224a801a7e53890035f03a841/1/1/110156-up3404va-kn073w-5.jpg",
            "https://nissei.com/media/catalog/product/cache/ef70040224a801a7e53890035f03a841/1/1/110156-up3404va-kn073w-4.jpg",
            "https://nissei.com/media/catalog/product/cache/ef70040224a801a7e53890035f03a841/1/1/110156-up3404va-kn073w-3.jpg",
            "https://nissei.com/media/catalog/product/cache/ef70040224a801a7e53890035f03a841/1/1/110156-up3404va-kn073w-2.jpg",
            "https://nissei.com/media/catalog/product/cache/ef70040224a801a7e53890035f03a841/1/1/110156-up3404va-kn073w-1.jpg"
        ],
        "id": 24
    },
    {
        "name": "Notebook Asus Vivobook X1605ZA-MB115W 16\" Intel Core i3-1215U 8 GB DDR4 512 GB SSD - Negro",
        "price": "Gs. 3.992.000",
        "details": {
            "Pantalla": "LED de 16\" WUXGA 1920 x 1200p",
            "Procesador": "Intel Core i3-1215U Hexa-Core 3.3 - 4.4 GHz",
            "Memoria RAM": "8 GB DDR4",
            "Memoria de almacenamiento": "SSD M.2 NVMe de 512 GB",
            "Gráficos": "Intel UHD",
            "Sistema operativo": "Windows 11 Home"
        },
        "label": "Asus",
        "categories": [
            "Notebooks Estudio",
            "Notebooks Trabajo"
        ],
        "srcImages": [
            "https://nissei.com/media/catalog/product/cache/ef70040224a801a7e53890035f03a841/1/1/110160-x1605za-mb012w-4_2.jpg",
            "https://nissei.com/media/catalog/product/cache/ef70040224a801a7e53890035f03a841/1/1/110160-x1605za-mb012w-3_2.jpg",
            "https://nissei.com/media/catalog/product/cache/ef70040224a801a7e53890035f03a841/1/1/110160-x1605za-mb012w-2_2.jpg",
            "https://nissei.com/media/catalog/product/cache/ef70040224a801a7e53890035f03a841/1/1/110160-x1605za-mb012w-1_2.jpg"
        ],
        "id": 25
    },
    {
        "name": "Notebook Dell Inspiron 15 3511 15.6\" Intel Core i5-1135G7 8 GB DDR4 256 SSD - Platinum Silver",
        "price": "Gs. 4.440.000",
        "details": {
            "Pantalla": "LED de 15.6\" Full HD 1920 x 1080p",
            "Procesador": "Intel Core i5-1135G7 Quad-Core 2.4 - 4.2 GHz",
            "Memoria RAM": "8 GB DDR4",
            "Memoria de almacenamiento": "SSD de 256 GB",
            "Gráficos": "Intel Iris Xe",
            "Sistema operativo": "Windows 11 Home"
        },
        "label": "HP",
        "categories": [
            "Notebooks Estudio",
            "Notebooks Trabajo"
        ],
        "srcImages": [
            "https://nissei.com/media/catalog/product/cache/ef70040224a801a7e53890035f03a841/1/1/111978-3511-5.jpg",
            "https://nissei.com/media/catalog/product/cache/ef70040224a801a7e53890035f03a841/1/1/111978-3511-4.jpg",
            "https://nissei.com/media/catalog/product/cache/ef70040224a801a7e53890035f03a841/1/1/111978-3511-3.jpg",
            "https://nissei.com/media/catalog/product/cache/ef70040224a801a7e53890035f03a841/1/1/111978-3511-2.jpg",
            "https://nissei.com/media/catalog/product/cache/ef70040224a801a7e53890035f03a841/1/1/111978-3511-1.jpg"
        ],
        "id": 26
    },
    {
        "name": "Notebook Asus Vivobook F1500EA-WB51 15.6\" Intel Core i5-1135G7 8 GB DDR4 256 GB SSD - Negro",
        "price": "Gs. 4.019.000",
        "details": {
            "Pantalla": "LED de 15.6\" Full HD 1920 x 1080p",
            "Procesador": "Intel Core i5-1135G7 Quad-Core 2.4 - 4.2 GHz",
            "Memoria RAM": "8 GB DDR4",
            "Memoria de almacenamiento": "SSD M.2 NVMe de 256 GB",
            "Gráficos": "Intel Iris Xe",
            "Sistema operativo": "Windows 11 Home"
        },
        "label": "Asus",
        "categories": [
            "Notebooks Estudio",
            "Notebooks Trabajo",
            "Ten to Ten"
        ],
        "srcImages": [
            "https://nissei.com/media/catalog/product/cache/ef70040224a801a7e53890035f03a841/1/1/111977-f1500ea-wb51-4.jpg",
            "https://nissei.com/media/catalog/product/cache/ef70040224a801a7e53890035f03a841/1/1/111977-f1500ea-wb51-3.jpg",
            "https://nissei.com/media/catalog/product/cache/ef70040224a801a7e53890035f03a841/1/1/111977-f1500ea-wb51-2.jpg",
            "https://nissei.com/media/catalog/product/cache/ef70040224a801a7e53890035f03a841/1/1/111977-f1500ea-wb51-1.jpg"
        ],
        "id": 27
    },
    {
        "name": "Notebook Lenovo ThinkPad E15 Gen 4 15.6\" AMD Ryzen 7 5825U - Mineral Metallic (21ED0043US)",
        "price": "Gs. 7.445.000",
        "details": {
            "Pantalla": "IPS de 15.6\" Full HD 1920 x 1080p",
            "Procesador": "AMD Ryzen 7 5825U Octa-Core 2.0 - 4.5 GHz",
            "Memoria RAM": "16 GB DDR4",
            "Memoria de almacenamiento": "SSD M.2 NVMe de 512 GB",
            "Gráficos": "AMD Ryzen",
            "Sistema Operativos": "Windows 11 Home"
        },
        "label": "Lenovo",
        "categories": [
            "Notebooks Estudio",
            "Notebooks Trabajo"
        ],
        "srcImages": [
            "https://nissei.com/media/catalog/product/cache/ef70040224a801a7e53890035f03a841/2/1/21e6007qus_-_1_1-111533.jpg",
            "https://nissei.com/media/catalog/product/cache/ef70040224a801a7e53890035f03a841/2/1/21e6007qus_-_1_1-111533-1.jpg",
            "https://nissei.com/media/catalog/product/cache/ef70040224a801a7e53890035f03a841/2/1/21e6007qus_-_1_1-111533-2.jpg",
            "https://nissei.com/media/catalog/product/cache/ef70040224a801a7e53890035f03a841/2/1/21e6007qus_-_1_1-111533-3.jpg",
            "https://nissei.com/media/catalog/product/cache/ef70040224a801a7e53890035f03a841/2/1/21e6007qus_-_1_1-111533-4.jpg"
        ],
        "id": 28
    },
    {
        "name": "Notebook HP 250 G8 15.6\" Intel Core i5-1135G7 8 GB DDR4 256 GB SSD - Negro",
        "price": "Gs. 3.902.000",
        "details": {
            "Pantalla": "LED de 15.6” HD 1366 x 768p",
            "Procesador": "Intel Core i5-1135G7 Quad-Core 2.4 - 4.2 GHz",
            "Memoria RAM": "8 GB DDR4",
            "Memoria de almacenamiento": "SSD M.2 NVMe de 256 GB",
            "Gráficos": "Intel Iris Xe",
            "Sistema operativo": "Windows 11 Home"
        },
        "label": "HP",
        "categories": [
            "Notebooks Estudio",
            "Notebooks Trabajo"
        ],
        "srcImages": [
            "https://nissei.com/media/catalog/product/cache/ef70040224a801a7e53890035f03a841/1/1/111606-4.jpg",
            "https://nissei.com/media/catalog/product/cache/ef70040224a801a7e53890035f03a841/1/1/111606-2.jpg",
            "https://nissei.com/media/catalog/product/cache/ef70040224a801a7e53890035f03a841/1/1/111606-3.jpg",
            "https://nissei.com/media/catalog/product/cache/ef70040224a801a7e53890035f03a841/1/1/111606-1.jpg",
            "https://nissei.com/media/catalog/product/cache/ef70040224a801a7e53890035f03a841/1/1/111606.jpg"
        ],
        "id": 29
    },
    {
        "name": "Notebook HP 240 G8 14\" Intel Core i3-1115G4 8 GB DDR4 1 TB HDD - Negro",
        "price": "Gs. 2.682.000",
        "details": {
            "Pantalla": "LED de 14\" HD 1366 x 768p",
            "Procesador": "Intel Core i3-1115G4 Dual-Core 3.0 - 4.1 GHz",
            "Memoria RAM": "8 GB DDR4",
            "Memoria de almacenamiento": "HDD de 1 TB",
            "Gráficos": "Intel UHD",
            "Sistema operativo": "Windows 10 Home"
        },
        "label": "HP",
        "categories": [
            "Notebooks Estudio",
            "Notebooks Trabajo"
        ],
        "srcImages": [
            "https://nissei.com/media/catalog/product/cache/ef70040224a801a7e53890035f03a841/1/1/111600-4.jpg",
            "https://nissei.com/media/catalog/product/cache/ef70040224a801a7e53890035f03a841/1/1/111600-3.jpg",
            "https://nissei.com/media/catalog/product/cache/ef70040224a801a7e53890035f03a841/1/1/111600-2.jpg",
            "https://nissei.com/media/catalog/product/cache/ef70040224a801a7e53890035f03a841/1/1/111600-1.jpg",
            "https://nissei.com/media/catalog/product/cache/ef70040224a801a7e53890035f03a841/1/1/111600.jpg"
        ],
        "id": 30
    },
    {
        "name": "Notebook Asus ROG Strix G16 G614JI-AS94 16\" Intel Core i9-13980HX RTX 4070 8 GB - Gris",
        "price": "Gs. 21.348.000",
        "details": {
            "Pantalla": "IPS de 16\" WUXGA 1920 x 1200p",
            "Procesador": "Intel Core i9-13980HX Tetractys-Core 2.2 - 5.6 GHz",
            "Memoria RAM": "DDR5 de 16 GB",
            "Memoria de almacenamiento": "SSD M.2 NVMe de 1 TB",
            "Gráficos": "NVIDIA GeForce RTX 4070 8 GB GDDR6",
            "Sistema operativo": "Windows 11 Home"
        },
        "label": "Asus",
        "categories": [
            "Notebooks Estudio",
            "Notebooks Trabajo"
        ],
        "srcImages": [
            "https://nissei.com/media/catalog/product/cache/ef70040224a801a7e53890035f03a841/1/1/111509-8_1.jpg",
            "https://nissei.com/media/catalog/product/cache/ef70040224a801a7e53890035f03a841/1/1/111509-7_1.jpg",
            "https://nissei.com/media/catalog/product/cache/ef70040224a801a7e53890035f03a841/1/1/111509-6_1.jpg",
            "https://nissei.com/media/catalog/product/cache/ef70040224a801a7e53890035f03a841/1/1/111509-5_1.jpg",
            "https://nissei.com/media/catalog/product/cache/ef70040224a801a7e53890035f03a841/1/1/111509-4_1.jpg",
            "https://nissei.com/media/catalog/product/cache/ef70040224a801a7e53890035f03a841/1/1/111509-3_1.jpg",
            "https://nissei.com/media/catalog/product/cache/ef70040224a801a7e53890035f03a841/1/1/111509-2_1.jpg",
            "https://nissei.com/media/catalog/product/cache/ef70040224a801a7e53890035f03a841/1/1/111509-1.jpg",
            "https://nissei.com/media/catalog/product/cache/ef70040224a801a7e53890035f03a841/1/1/111509.jpg"
        ],
        "id": 31
    },
    {
        "name": "Notebook Lenovo Legion Pro 7 16IRX8H 16\" Intel Core i9-13980HX RTX 4080 12 GB - Onyx Grey (82WQ002SUS)",
        "price": "Gs. 27.357.000",
        "details": {
            "Pantalla": "IPS de 16\" WQXGA 2560 x 1600p",
            "Procesador": "Intel Core i9-13980HX Tetractys-Core 2.0 - 5.4 GHz",
            "Memoria RAM": "DDR5 de 16 GB",
            "Memoria de almacenamiento": "SSD M.2 NVMe de 1 TB",
            "Gráficos": "NVIDIA GeForce GTX 4080 12 GB GDDR6",
            "Sistema operativo": "Windows 11 Home"
        },
        "label": "Lenovo",
        "categories": [
            "Notebooks Estudio",
            "Notebooks Trabajo"
        ],
        "srcImages": [
            "https://nissei.com/media/catalog/product/cache/ef70040224a801a7e53890035f03a841/1/1/111511-112.jpg",
            "https://nissei.com/media/catalog/product/cache/ef70040224a801a7e53890035f03a841/1/1/111511-11.jpg",
            "https://nissei.com/media/catalog/product/cache/ef70040224a801a7e53890035f03a841/1/1/111511-10.jpg",
            "https://nissei.com/media/catalog/product/cache/ef70040224a801a7e53890035f03a841/1/1/111511-9.jpg",
            "https://nissei.com/media/catalog/product/cache/ef70040224a801a7e53890035f03a841/1/1/111511-8.jpg",
            "https://nissei.com/media/catalog/product/cache/ef70040224a801a7e53890035f03a841/1/1/111511-7.jpg",
            "https://nissei.com/media/catalog/product/cache/ef70040224a801a7e53890035f03a841/1/1/111511-6.jpg",
            "https://nissei.com/media/catalog/product/cache/ef70040224a801a7e53890035f03a841/1/1/111511-5.jpg",
            "https://nissei.com/media/catalog/product/cache/ef70040224a801a7e53890035f03a841/1/1/111511-4.jpg",
            "https://nissei.com/media/catalog/product/cache/ef70040224a801a7e53890035f03a841/1/1/111511-3.jpg",
            "https://nissei.com/media/catalog/product/cache/ef70040224a801a7e53890035f03a841/1/1/111511-2.jpg",
            "https://nissei.com/media/catalog/product/cache/ef70040224a801a7e53890035f03a841/1/1/111511-1.jpg",
            "https://nissei.com/media/catalog/product/cache/ef70040224a801a7e53890035f03a841/1/1/111511.jpg"
        ],
        "id": 32
    },
    {
        "name": "Notebook Asus Vivobook Pro 15 M6500QH-DB51 15.6\" AMD Ryzen 5 5600H GTX 1650 4 GB - Quiet Blue",
        "price": "Gs. 5.606.000",
        "details": {
            "Pantalla": "IPS de 15.6\" FHD 1920 x 1080p",
            "Procesador": "AMD Ryzen 5 5600H Hexa-Core 3.3 - 4.2 GHz",
            "Memoria RAM": "DDR4 de 8 GB",
            "Memoria de almacenamiento": "SSD M.2 NVMe de 512 GB",
            "Gráficos": "NVIDIA GeForce GTX 1650 4 GB GDDR6",
            "Sistema operativo": "Windows 11 Home"
        },
        "label": "Asus",
        "categories": [
            "Notebooks Estudio",
            "Notebooks Trabajo"
        ],
        "srcImages": [
            "https://nissei.com/media/catalog/product/cache/ef70040224a801a7e53890035f03a841/1/1/111242-7.jpg",
            "https://nissei.com/media/catalog/product/cache/ef70040224a801a7e53890035f03a841/1/1/111242-6.jpg",
            "https://nissei.com/media/catalog/product/cache/ef70040224a801a7e53890035f03a841/1/1/111242-5.jpg",
            "https://nissei.com/media/catalog/product/cache/ef70040224a801a7e53890035f03a841/1/1/111242-4.jpg",
            "https://nissei.com/media/catalog/product/cache/ef70040224a801a7e53890035f03a841/1/1/111242-3.jpg",
            "https://nissei.com/media/catalog/product/cache/ef70040224a801a7e53890035f03a841/1/1/111242-2.jpg",
            "https://nissei.com/media/catalog/product/cache/ef70040224a801a7e53890035f03a841/1/1/111242-1.jpg",
            "https://nissei.com/media/catalog/product/cache/ef70040224a801a7e53890035f03a841/1/1/111242.jpg"
        ],
        "id": 33
    },
    {
        "name": "Notebook Samsung Galaxy Book NP750XDA-KD1US 15.6\" Intel Core i5-1135G7 8 GB LPDDR4 256 SSD - Mystic Silver + Estuche Case Logic VNAI-215 - Negro",
        "price": "Gs. 4.126.000",
        "details": {
            "Pantalla": "LED de 15.6\" Full HD 1920 x 1080p",
            "Procesador": "Intel Core i5-1135G7 Quad-Core 2.4 - 4.2 GHz",
            "Memoria RAM": "LPDDR4X de 8 GB",
            "Memoria de almacenamiento": "SSD de 256 GB",
            "Gráficos": "Intel Iris Xe",
            "Sistema operativo": "Windows 11 Pro"
        },
        "label": "Samsung",
        "categories": [
            "Notebooks Estudio",
            "Notebooks Trabajo"
        ],
        "srcImages": [
            "https://nissei.com/media/catalog/product/cache/ef70040224a801a7e53890035f03a841/1/1/111302-9.jpg",
            "https://nissei.com/media/catalog/product/cache/ef70040224a801a7e53890035f03a841/1/1/111302-8.jpg",
            "https://nissei.com/media/catalog/product/cache/ef70040224a801a7e53890035f03a841/1/1/111302-7.jpg",
            "https://nissei.com/media/catalog/product/cache/ef70040224a801a7e53890035f03a841/1/1/111302-6.jpg",
            "https://nissei.com/media/catalog/product/cache/ef70040224a801a7e53890035f03a841/1/1/111302-5.jpg",
            "https://nissei.com/media/catalog/product/cache/ef70040224a801a7e53890035f03a841/1/1/111302-4.jpg",
            "https://nissei.com/media/catalog/product/cache/ef70040224a801a7e53890035f03a841/1/1/111302-3.jpg",
            "https://nissei.com/media/catalog/product/cache/ef70040224a801a7e53890035f03a841/1/1/111302-2.jpg",
            "https://nissei.com/media/catalog/product/cache/ef70040224a801a7e53890035f03a841/1/1/111302-1.jpg",
            "https://nissei.com/media/catalog/product/cache/ef70040224a801a7e53890035f03a841/1/1/111302.jpg"
        ],
        "id": 34
    },
    {
        "name": "Notebook MSI Pulse GL76 12UEK-052 17.3\" Intel Core i7-12700H RTX 3060 6 GB GDDR6 - Gris/Negro",
        "price": "Gs. 10.540.000",
        "details": {
            "Pantalla": "IPS de 17.3\" FHD 1920 x 1080p 144 Hz",
            "Procesador": "Intel Core i7-12700H Tetradeca-Core 1.7 - 4.7 GHz",
            "Memoria RAM": "DDR4 de 16 GB",
            "Memoria de almacenamiento": "SSD M.2 NVMe de 512 GB",
            "Gráficos": "NVIDIA GeForce RTX 3060 6 GB GDDR6",
            "Sistema operativo": "Windows 11 Home"
        },
        "label": "MSI",
        "categories": [
            "Notebooks Estudio",
            "Notebooks Trabajo"
        ],
        "srcImages": [
            "https://nissei.com/media/catalog/product/cache/ef70040224a801a7e53890035f03a841/1/1/111051-4.jpg",
            "https://nissei.com/media/catalog/product/cache/ef70040224a801a7e53890035f03a841/1/1/111051-3.jpg",
            "https://nissei.com/media/catalog/product/cache/ef70040224a801a7e53890035f03a841/1/1/111051-2.jpg",
            "https://nissei.com/media/catalog/product/cache/ef70040224a801a7e53890035f03a841/1/1/111051-1.jpg",
            "https://nissei.com/media/catalog/product/cache/ef70040224a801a7e53890035f03a841/1/1/111051.jpg"
        ],
        "id": 35
    },
    {
        "name": "Notebook HP 15-EF2514LA 15.6\" AMD Ryzen 7 5700U 8 GB DDR4 512 GB SSD - Dorado",
        "price": "Gs. 5.275.000",
        "details": {
            "Pantalla": "LED de 15.6\" HD 1366 x 768p",
            "Procesador": "AMD Ryzen 7 5700U Octa-Core 1.8 - 4.3 GHz",
            "Memoria RAM": "DDR4 de 8 GB",
            "Memoria de almacenamiento": "SSD M.2 NVMe de 512 GB",
            "Gráficos": "AMD Radeon",
            "Sistema operativo": "Windows 11 Home"
        },
        "label": "HP",
        "categories": [
            "Notebooks Estudio",
            "Notebooks Trabajo"
        ],
        "srcImages": [
            "https://nissei.com/media/catalog/product/cache/ef70040224a801a7e53890035f03a841/1/1/111132-3.jpg",
            "https://nissei.com/media/catalog/product/cache/ef70040224a801a7e53890035f03a841/1/1/111132-2.jpg",
            "https://nissei.com/media/catalog/product/cache/ef70040224a801a7e53890035f03a841/1/1/111132-1.jpg",
            "https://nissei.com/media/catalog/product/cache/ef70040224a801a7e53890035f03a841/1/1/111132.jpg"
        ],
        "id": 36
    },
    {
        "name": "Notebook Lenovo Ideapad Flex 5 16IAU7 16\" Intel Core i7-1255U 16 GB LPDDR4x 512 GB SSD - Storm Grey (82R80002US)",
        "price": "Gs. 7.167.000",
        "details": {
            "Pantalla": "IPS táctil de 16\" 2.5K 2560 x 1600p",
            "Procesador": "Intel Core i7-1255U Deca-Core 1.7 - 4.7 GHz",
            "Memoria RAM": "LPDDR4x de 16 GB",
            "Memoria de almacenamiento": "SSD M.2 NVMe de 512 GB",
            "Gráficos": "Intel Iris Xe",
            "Sistema operativo": "Windows 11 Home"
        },
        "label": "Lenovo",
        "categories": [
            "Notebooks Estudio",
            "Notebooks Trabajo"
        ],
        "srcImages": [
            "https://nissei.com/media/catalog/product/cache/ef70040224a801a7e53890035f03a841/1/1/110918-8.jpg",
            "https://nissei.com/media/catalog/product/cache/ef70040224a801a7e53890035f03a841/1/1/110918-7.jpg",
            "https://nissei.com/media/catalog/product/cache/ef70040224a801a7e53890035f03a841/1/1/110918-6.jpg",
            "https://nissei.com/media/catalog/product/cache/ef70040224a801a7e53890035f03a841/1/1/110918-5.jpg",
            "https://nissei.com/media/catalog/product/cache/ef70040224a801a7e53890035f03a841/1/1/110918-4.jpg",
            "https://nissei.com/media/catalog/product/cache/ef70040224a801a7e53890035f03a841/1/1/110918-3.jpg",
            "https://nissei.com/media/catalog/product/cache/ef70040224a801a7e53890035f03a841/1/1/110918-2.jpg",
            "https://nissei.com/media/catalog/product/cache/ef70040224a801a7e53890035f03a841/1/1/110918-1.jpg",
            "https://nissei.com/media/catalog/product/cache/ef70040224a801a7e53890035f03a841/1/1/110918.jpg"
        ],
        "id": 37
    }
]